lade/__init__.py
lade/decoding.py
lade/lade_distributed.py
lade/utils.py
lade/models/modeling_llama.py
lade_gml-0.0.4.dist-info/licenses/LICENSE
lade_gml-0.0.4.dist-info/METADATA
lade_gml-0.0.4.dist-info/WHEEL
lade_gml-0.0.4.dist-info/top_level.txt
lade_gml-0.0.4.dist-info/RECORD
