Metadata-Version: 2.4
Name: lade-gml
Version: 0.0.4
Summary: Lookahead Decoding Implementation
Home-page: https://github.com/gimletlabs/LookaheadDecoding.git
Author: Fu Yichao
Author-email: yichaofu2000@outlook.com
License: Apache-2
License-File: LICENSE
Requires-Dist: transformers==4.36.2
Requires-Dist: accelerate==0.23.0
Requires-Dist: fschat==0.2.31
Requires-Dist: openai
Requires-Dist: anthropic
Requires-Dist: einops==0.7.0
Requires-Dist: torch<2.1.1
Dynamic: author
Dynamic: author-email
Dynamic: home-page
Dynamic: license
Dynamic: license-file
Dynamic: requires-dist
Dynamic: summary
